[
        {
                "name": "3d",
                "extensions": [
                        ".stl",
                        ".obj",
                        ".fbx",
                        ".3mf",
                        ".gltf",
                        ".glb",
                        ".dae",
                        ".step",
                        ".stp",
                        ".skp",
                        ".3ds",
                        ".blend"
                ]
        },
        {
                "name": "audio",
                "extensions": [
                        ".wav",
                        ".aiff",
                        ".flac",
                        ".alac",
                        ".mp3",
                        ".aac",
                        ".m4a",
                        ".ogg"
                ]
        },
        {
                "name": "code",
                "extensions": [
                        ".py",
                        ".pyc",
                        ".pyd",
                        ".pyo",
                        ".c",
                        ".h",
                        ".cpp",
                        ".cxx",
                        ".c++",
                        ".hpp",
                        ".hxx",
                        ".h++",
                        ".java",
                        ".class",
                        ".jar",
                        ".jks",
                        ".javadoc",
                        ".cs",
                        ".csproj",
                        ".dll",
                        ".js",
                        ".jsx",
                        ".ts",
                        ".tsx",
                        ".vb",
                        ".vbp",
                        ".frm",
                        ".frx",
                        ".vbg",
                        ".vbw",
                        ".vbl",
                        ".vbr",
                        ".go",
                        ".gohtml",
                        ".tmpl",
                        ".pas",
                        ".pp",
                        ".f",
                        ".for",
                        ".ftn",
                        ".pl",
                        ".pm",
                        ".t",
                        ".pod",
                        ".r",
                        ".rproj",
                        ".rdata",
                        ".rda",
                        ".rds",
                        ".rhistory",
                        ".php",
                        ".phtml",
                        ".inc",
                        ".phps",
                        ".php3",
                        ".php4",
                        ".php5",
                        ".php7",
                        ".asm",
                        ".s",
                        ".S",
                        ".sx",
                        ".rs",
                        ".rlib",
                        ".m",
                        ".mat",
                        ".mlx",
                        ".ada",
                        ".adb",
                        ".ads",
                        ".kt",
                        ".swift",
                        ".cbl",
                        ".rb",
                        ".dart",
                        ".sh",
                        ".bash",
                        ".zsh",
                        ".hs",
                        ".lhs",
                        ".lsp",
                        ".lisp",
                        ".el",
                        ".jl",
                        ".m",
                        ".mm",
                        ".scala",
                        ".sc",
                        ".ex",
                        ".exs",
                        ".zig",
                        ".zir",
                        ".zigr",
                        ".zon",
                        ".psm1",
                        ".psd1",
                        ".erl",
                        ".hrl"
                ]
        },
        {
                "name": "data",
                "extensions": [
                        ".dat",
                        ".csv",
                        ".xml",
                        ".json",
                        ".db",
                        ".sql",
                        ".log",
                        ".sav"
                ]
        },
        {
                "name": "documents",
                "extensions": [
                        ".docx",
                        ".doc",
                        ".pdf",
                        ".pptx",
                        ".ppt",
                        ".xlsx",
                        ".xls",
                        ".txt",
                        ".rtf",
                        ".odt",
                        ".ods",
                        ".odp",
                        ".opg",
                        ".odb",
                        ".odf"
                ]
        },
        {
                "name": "image",
                "extensions": [
                        ".jpg",
                        ".jpeg",
                        ".png",
                        ".gif",
                        ".tiff",
                        ".webp",
                        ".bmp",
                        ".avif",
                        ".svg",
                        ".raw",
                        ".cr2",
                        ".nef",
                        ".ai",
                        ".ico",
                        ".cur",
                        ".tif",
                        ".eps"
                ]
        },
        {
                "name": "markup",
                "extensions": [
                        ".html",
                        ".md",
                        ".markdown",
                        ".sgml",
                        ".xhtml",
                        ".css",
                        ".mathml",
                        ".tex",
                        ".docker"
                ]
        },
        {
                "name": "video",
                "extensions": [
                        ".mp4",
                        ".mov",
                        ".avi",
                        ".wmv",
                        ".mkv",
                        ".webm",
                        ".flv",
                        ".mts",
                        ".m2ts"
                ]
        }
]
